darca_executor/__init__.py
darca_executor/__version__.py
darca_executor/executor.py
darca_executor-0.1.0.dist-info/LICENSE
darca_executor-0.1.0.dist-info/METADATA
darca_executor-0.1.0.dist-info/WHEEL
darca_executor-0.1.0.dist-info/RECORD
